<?xml version="1.0" encoding="utf-8"?>
<SoundBanksInfo Platform="Windows" BasePlatform="Windows" SchemaVersion="12" SoundbankVersion="140">
	<RootPaths>
		<ProjectRoot>/Users/joon_0/Library/Application Support/Wwise2019/Bottles/Wwise2019x64/dosdevices/y:/Documents/GitHub/DesLike/DESLIKE/DESLIKE_WwiseProject/</ProjectRoot>
		<SourceFilesRoot>/Users/joon_0/Library/Application Support/Wwise2019/Bottles/Wwise2019x64/dosdevices/y:/Documents/GitHub/DesLike/DESLIKE/DESLIKE_WwiseProject/.cache/Windows/</SourceFilesRoot>
		<SoundBanksRoot>/Users/joon_0/Library/Application Support/Wwise2019/Bottles/Wwise2019x64/dosdevices/y:/Documents/GitHub/DesLike/DESLIKE/Assets/StreamingAssets/Audio/</SoundBanksRoot>
		<ExternalSourcesInputFile></ExternalSourcesInputFile>
		<ExternalSourcesOutputRoot>/Users/joon_0/Library/Application Support/Wwise2019/Bottles/Wwise2019x64/dosdevices/y:/Documents/GitHub/DesLike/DESLIKE/DESLIKE_WwiseProject/GeneratedSoundBanks/Windows</ExternalSourcesOutputRoot>
	</RootPaths>
	<DialogueEvents/>
	<StreamedFiles/>
	<MediaFilesNotInAnyBank/>
	<SoundBanks>
		<SoundBank Id="1355168291" Language="SFX" Hash="21620069">
			<ObjectPath>Init</ObjectPath>
			<ShortName>Init</ShortName>
			<Path>Init.bnk</Path>
		</SoundBank>
		<SoundBank Id="3161908922" Language="SFX" Hash="188790486">
			<ObjectPath>\SoundBanks\Default Work Unit\main</ObjectPath>
			<ShortName>main</ShortName>
			<Path>main.bnk</Path>
			<IncludedEvents>
				<Event Id="461545889" Name="Battle_End" ObjectPath="\Events\Default Work Unit\Battle_End" MaxAttenuation="0." DurationType="OneShot" DurationMin="0." DurationMax="0."/>
				<Event Id="2706291346" Name="Battle_Start" ObjectPath="\Events\Default Work Unit\Battle_Start" DurationType="OneShot" DurationMin="136.130417" DurationMax="136.130417">
					<IncludedMemoryFiles>
						<File Id="62381386" Language="SFX">
							<ShortName>Escaping the Ruins W.wav</ShortName>
							<Path>SFX/Escaping the Ruins W_9733FE50.wem</Path>
						</File>
					</IncludedMemoryFiles>
				</Event>
				<Event Id="3025390842" Name="H_23101_Die" ObjectPath="\Events\Default Work Unit\H_23101_Die" DurationType="OneShot" DurationMin="3.940282" DurationMax="4.552415">
					<IncludedMemoryFiles>
						<File Id="234665702" Language="SFX">
							<ShortName>23101_Die_Print_01.wav</ShortName>
							<Path>SFX/23101_Die_Print_01_10C4C929.wem</Path>
						</File>
						<File Id="554435908" Language="SFX">
							<ShortName>GameOver_Print_01.wav</ShortName>
							<Path>SFX/GameOver_Print_01_10C4C929.wem</Path>
						</File>
					</IncludedMemoryFiles>
				</Event>
				<Event Id="2377059575" Name="H_23101_Skill_1" ObjectPath="\Events\Default Work Unit\H_23101_Skill_1" DurationType="OneShot" DurationMin="4.084604" DurationMax="4.084604">
					<IncludedMemoryFiles>
						<File Id="797527484" Language="SFX">
							<ShortName>23101_Skill_1_Print_01.wav</ShortName>
							<Path>SFX/23101_Skill_1_Print_01_10C4C929.wem</Path>
						</File>
					</IncludedMemoryFiles>
				</Event>
				<Event Id="2377059572" Name="H_23101_Skill_2" ObjectPath="\Events\Default Work Unit\H_23101_Skill_2" DurationType="OneShot" DurationMin="3.3165" DurationMax="3.3165">
					<IncludedMemoryFiles>
						<File Id="290311062" Language="SFX">
							<ShortName>23101_Skill_2_Print_01.wav</ShortName>
							<Path>SFX/23101_Skill_2_Print_01_10C4C929.wem</Path>
						</File>
					</IncludedMemoryFiles>
				</Event>
				<Event Id="490612746" Name="Is_Pause" ObjectPath="\Events\Default Work Unit\Is_Pause" MaxAttenuation="0." DurationType="OneShot" DurationMin="0." DurationMax="0."/>
				<Event Id="2370616541" Name="Is_Resume" ObjectPath="\Events\Default Work Unit\Is_Resume" MaxAttenuation="0." DurationType="OneShot" DurationMin="0." DurationMax="0."/>
			</IncludedEvents>
		</SoundBank>
	</SoundBanks>
</SoundBanksInfo>
